odoo9_addon_l10n_es_aeat_mod390-9.0.1.1.0-py2.7-nspkg.pth
odoo9_addon_l10n_es_aeat_mod390-9.0.1.1.0.dist-info/METADATA
odoo9_addon_l10n_es_aeat_mod390-9.0.1.1.0.dist-info/RECORD
odoo9_addon_l10n_es_aeat_mod390-9.0.1.1.0.dist-info/WHEEL
odoo9_addon_l10n_es_aeat_mod390-9.0.1.1.0.dist-info/namespace_packages.txt
odoo9_addon_l10n_es_aeat_mod390-9.0.1.1.0.dist-info/top_level.txt
odoo_addons/l10n_es_aeat_mod390/README.rst
odoo_addons/l10n_es_aeat_mod390/__init__.py
odoo_addons/l10n_es_aeat_mod390/__openerp__.py
odoo_addons/l10n_es_aeat_mod390/data/aeat_export_mod390_main_data.xml
odoo_addons/l10n_es_aeat_mod390/data/aeat_export_mod390_sub01_data.xml
odoo_addons/l10n_es_aeat_mod390/data/aeat_export_mod390_sub02_data.xml
odoo_addons/l10n_es_aeat_mod390/data/aeat_export_mod390_sub03_data.xml
odoo_addons/l10n_es_aeat_mod390/data/aeat_export_mod390_sub04_data.xml
odoo_addons/l10n_es_aeat_mod390/data/aeat_export_mod390_sub05_data.xml
odoo_addons/l10n_es_aeat_mod390/data/aeat_export_mod390_sub06_data.xml
odoo_addons/l10n_es_aeat_mod390/data/aeat_export_mod390_sub07_data.xml
odoo_addons/l10n_es_aeat_mod390/data/aeat_export_mod390_sub08_data.xml
odoo_addons/l10n_es_aeat_mod390/data/tax_code_map_mod390_data.xml
odoo_addons/l10n_es_aeat_mod390/docs/dr390e2017v3.xlsx
odoo_addons/l10n_es_aeat_mod390/docs/instr390.pdf
odoo_addons/l10n_es_aeat_mod390/i18n/ca.po
odoo_addons/l10n_es_aeat_mod390/i18n/es.po
odoo_addons/l10n_es_aeat_mod390/i18n/l10n_es_aeat_mod390.pot
odoo_addons/l10n_es_aeat_mod390/models/__init__.py
odoo_addons/l10n_es_aeat_mod390/models/mod390.py
odoo_addons/l10n_es_aeat_mod390/readme/CONTRIBUTORS.rst
odoo_addons/l10n_es_aeat_mod390/readme/CREDITS.rst
odoo_addons/l10n_es_aeat_mod390/readme/DESCRIPTION.rst
odoo_addons/l10n_es_aeat_mod390/readme/INSTALL.rst
odoo_addons/l10n_es_aeat_mod390/readme/ROADMAP.rst
odoo_addons/l10n_es_aeat_mod390/readme/USAGE.rst
odoo_addons/l10n_es_aeat_mod390/security/ir.model.access.csv
odoo_addons/l10n_es_aeat_mod390/security/l10n_es_aeat_mod390_security.xml
odoo_addons/l10n_es_aeat_mod390/static/description/icon.png
odoo_addons/l10n_es_aeat_mod390/static/description/icon.svg
odoo_addons/l10n_es_aeat_mod390/static/description/index.html
odoo_addons/l10n_es_aeat_mod390/tests/__init__.py
